projeto/nivel1/nivel2/BCDto7SEGMENT.v

module full_leds ( 
    input [3:0]sec_ones,
    input [3:0]sec_tens,
    input [3:0]mins,
    output [6:0]sec_ones_segs,
    output [6:0]sec_tens_segs,
    output [6:0]min_segs
);

BCDto7SEGMENT secs(.E(sec_ones[3:0]),.S(sec_ones_segs[6:0]));
BCDto7SEGMENT tens(.E(sec_tens[3:0]),.S(sec_tens_segs[6:0]));
BCDto7SEGMENT minutes(.E(mins[3:0]),.S(min_segs[6:0]));

endmodule

module BCDto7SEGMENT(input wire[3:0]E,
                output reg [6:0]S);



always @(*)
 begin
  case(E)
   4'b0000 : S=7'b0000001; 
   4'b0001 : S=7'b1001111;
   4'b0010 : S=7'b0010010;
   4'b0011 : S=7'b0000110;
   4'b0100 : S=7'b1001100;
   4'b0101 : S=7'b0100100;
   4'b0110 : S=7'b0100000;
   4'b0111 : S=7'b0001101;
   4'b1000 : S=7'b0000000;
   4'b1001 : S=7'b0000100; 
   default : S=7'b1111111;
  endcase
 end

endmodule

projeto/nivel1/nivel2/BCDto7SEGMENT_tb.v
module BCDto7SEGMENT_tb();

reg [3:0] bcd;
    wire [6:0] seg;
    integer i;

    // Instantiate the Unit Under Test (UUT)
    BCDto7SEGMENT uut (
        .E(bcd), 
        .S(seg)
    );

//Apply inputs
    initial begin
        for(i = 0;i < 16;i = i+1) //run loop for 0 to 15.
        begin
            bcd = i;
            $display("seg = %b ",seg); 
            #10; //wait for 10 ns
        end
    end

    initial begin
        $dumpfile("bcdto7SEGMENT_tb.vcd");
        $dumpvars(0,BCDto7SEGMENT_tb);

    end
    

endmodule

projeto/nivel1/nivel2/bcdto7SEGMENT_tb.vcd
$date
	Fri Apr 30 12:13:09 2021
$end
$version
	Icarus Verilog
$end
$timescale
	1s
$end
$scope module BCDto7SEGMENT_tb $end
$var wire 7 ! seg [6:0] $end
$var reg 4 " bcd [3:0] $end
$var integer 32 # i [31:0] $end
$scope module uut $end
$var wire 4 $ E [3:0] $end
$var reg 7 % S [6:0] $end
$upscope $end
$upscope $end
$enddefinitions $end
#0
$dumpvars
b1 %
b0 $
b0 #
b0 "
b1 !
$end
#10
b1001111 !
b1001111 %
b1 "
b1 $
b1 #
#20
b10010 !
b10010 %
b10 "
b10 $
b10 #
#30
b110 !
b110 %
b11 "
b11 $
b11 #
#40
b1001100 !
b1001100 %
b100 "
b100 $
b100 #
#50
b100100 !
b100100 %
b101 "
b101 $
b101 #
#60
b100000 !
b100000 %
b110 "
b110 $
b110 #
#70
b1101 !
b1101 %
b111 "
b111 $
b111 #
#80
b0 !
b0 %
b1000 "
b1000 $
b1000 #
#90
b100 !
b100 %
b1001 "
b1001 $
b1001 #
#100
b1111111 !
b1111111 %
b1010 "
b1010 $
b1010 #
#110
b1011 "
b1011 $
b1011 #
#120
b1100 "
b1100 $
b1100 #
#130
b1101 "
b1101 $
b1101 #
#140
b1110 "
b1110 $
b1110 #
#150
b1111 "
b1111 $
b1111 #
#160
b10000 #
