projeto/nivel1/nivel2/nivel3/clockdiv100.v
`timescale 1ms/1ms
module clockdiv100 (clk, clk_out);
 
input clk;

output clk_out;
 
reg [24:0] r_reg;
wire [24:0] r_nxt;
reg clk_track;


initial begin
        r_reg <= 0;
	clk_track <= 1'b0;
end

always @(posedge clk)
 
begin
   if (r_nxt == 50)
 	   begin
	     r_reg <= 0;
	     clk_track <= ~clk_track;
	   end
 
  else 
      r_reg <= r_nxt;
end
 
 assign r_nxt = r_reg+1;   	      
 assign clk_out = clk_track;
endmodule

projeto/nivel1/nivel2/nivel3/clockdiv100_tb.v
`timescale 1ms/1ms
module clock_tb;
  reg clk;
  wire clk_out;
 
     clockdiv100 t1(clk,clk_out);
        initial
          clk= 1'b0;
     always
        #5  clk=~clk; 
        initial
            begin
               
               #10000 $finish;
            end
 
        initial
               $monitor("clk=%b,clk_out=%b",clk,clk_out);
 
        initial
            begin
              $dumpfile("clock_tb.vcd");
              $dumpvars(0,clock_tb);
             end
    endmodule

projeto/nivel1/nivel2/nivel3/clock_tb.vcd
$date
	Fri Apr 30 00:44:05 2021
$end
$version
	Icarus Verilog
$end
$timescale
	1ms
$end
$scope module clock_tb $end
$var wire 1 ! clk_out $end
$var reg 1 " clk $end
$scope module t1 $end
$var wire 1 " clk $end
$var wire 1 ! clk_out $end
$var wire 25 # r_nxt [24:0] $end
$var reg 1 $ clk_track $end
$var reg 25 % r_reg [24:0] $end
$upscope $end
$upscope $end
$enddefinitions $end
#0
$dumpvars
b0 %
0$
b1 #
0"
0!
$end
#5
b10 #
b1 %
1"
#10
0"
#15
b11 #
b10 %
1"
#20
0"
#25
b100 #
b11 %
1"
#30
0"
#35
b101 #
b100 %
1"
#40
0"
#45
b110 #
b101 %
1"
#50
0"
#55
b111 #
b110 %
1"
#60
0"
#65
b1000 #
b111 %
1"
#70
0"
#75
b1001 #
b1000 %
1"
#80
0"
#85
b1010 #
b1001 %
1"
#90
0"
#95
b1011 #
b1010 %
1"
#100
0"
#105
b1100 #
b1011 %
1"
#110
0"
#115
b1101 #
b1100 %
1"
#120
0"
#125
b1110 #
b1101 %
1"
#130
0"
#135
b1111 #
b1110 %
1"
#140
0"
#145
b10000 #
b1111 %
1"
#150
0"
#155
b10001 #
b10000 %
1"
#160
0"
#165
b10010 #
b10001 %
1"
#170
0"
#175
b10011 #
b10010 %
1"
#180
0"
#185
b10100 #
b10011 %
1"
#190
0"
#195
b10101 #
b10100 %
1"
#200
0"
#205
b10110 #
b10101 %
1"
#210
0"
#215
b10111 #
b10110 %
1"
#220
0"
#225
b11000 #
b10111 %
1"
#230
0"
#235
b11001 #
b11000 %
1"
#240
0"
#245
b11010 #
b11001 %
1"
#250
0"
#255
b11011 #
b11010 %
1"
#260
0"
#265
b11100 #
b11011 %
1"
#270
0"
#275
b11101 #
b11100 %
1"
#280
0"
#285
b11110 #
b11101 %
1"
#290
0"
#295
b11111 #
b11110 %
1"
#300
0"
#305
b100000 #
b11111 %
1"
#310
0"
#315
b100001 #
b100000 %
1"
#320
0"
#325
b100010 #
b100001 %
1"
#330
0"
#335
b100011 #
b100010 %
1"
#340
0"
#345
b100100 #
b100011 %
1"
#350
0"
#355
b100101 #
b100100 %
1"
#360
0"
#365
b100110 #
b100101 %
1"
#370
0"
#375
b100111 #
b100110 %
1"
#380
0"
#385
b101000 #
b100111 %
1"
#390
0"
#395
b101001 #
b101000 %
1"
#400
0"
#405
b101010 #
b101001 %
1"
#410
0"
#415
b101011 #
b101010 %
1"
#420
0"
#425
b101100 #
b101011 %
1"
#430
0"
#435
b101101 #
b101100 %
1"
#440
0"
#445
b101110 #
b101101 %
1"
#450
0"
#455
b101111 #
b101110 %
1"
#460
0"
#465
b110000 #
b101111 %
1"
#470
0"
#475
b110001 #
b110000 %
1"
#480
0"
#485
b110010 #
b110001 %
1"
#490
0"
#495
1!
1$
b1 #
b0 %
1"
#500
0"
#505
b10 #
b1 %
1"
#510
0"
#515
b11 #
b10 %
1"
#520
0"
#525
b100 #
b11 %
1"
#530
0"
#535
b101 #
b100 %
1"
#540
0"
#545
b110 #
b101 %
1"
#550
0"
#555
b111 #
b110 %
1"
#560
0"
#565
b1000 #
b111 %
1"
#570
0"
#575
b1001 #
b1000 %
1"
#580
0"
#585
b1010 #
b1001 %
1"
#590
0"
#595
b1011 #
b1010 %
1"
#600
0"
#605
b1100 #
b1011 %
1"
#610
0"
#615
b1101 #
b1100 %
1"
#620
0"
#625
b1110 #
b1101 %
1"
#630
0"
#635
b1111 #
b1110 %
1"
#640
0"
#645
b10000 #
b1111 %
1"
#650
0"
#655
b10001 #
b10000 %
1"
#660
0"
#665
b10010 #
b10001 %
1"
#670
0"
#675
b10011 #
b10010 %
1"
#680
0"
#685
b10100 #
b10011 %
1"
#690
0"
#695
b10101 #
b10100 %
1"
#700
0"
#705
b10110 #
b10101 %
1"
#710
0"
#715
b10111 #
b10110 %
1"
#720
0"
#725
b11000 #
b10111 %
1"
#730
0"
#735
b11001 #
b11000 %
1"
#740
0"
#745
b11010 #
b11001 %
1"
#750
0"
#755
b11011 #
b11010 %
1"
#760
0"
#765
b11100 #
b11011 %
1"
#770
0"
#775
b11101 #
b11100 %
1"
#780
0"
#785
b11110 #
b11101 %
1"
#790
0"
#795
b11111 #
b11110 %
1"
#800
0"
#805
b100000 #
b11111 %
1"
#810
0"
#815
b100001 #
b100000 %
1"
#820
0"
#825
b100010 #
b100001 %
1"
#830
0"
#835
b100011 #
b100010 %
1"
#840
0"
#845
b100100 #
b100011 %
1"
#850
0"
#855
b100101 #
b100100 %
1"
#860
0"
#865
b100110 #
b100101 %
1"
#870
0"
#875
b100111 #
b100110 %
1"
#880
0"
#885
b101000 #
b100111 %
1"
#890
0"
#895
b101001 #
b101000 %
1"
#900
0"
#905
b101010 #
b101001 %
1"
#910
0"
#915
b101011 #
b101010 %
1"
#920
0"
#925
b101100 #
b101011 %
1"
#930
0"
#935
b101101 #
b101100 %
1"
#940
0"
#945
b101110 #
b101101 %
1"
#950
0"
#955
b101111 #
b101110 %
1"
#960
0"
#965
b110000 #
b101111 %
1"
#970
0"
#975
b110001 #
b110000 %
1"
#980
0"
#985
b110010 #
b110001 %
1"
#990
0"
#995
0!
0$
b1 #
b0 %
1"
#1000
0"
#1005
b10 #
b1 %
1"
#1010
0"
#1015
b11 #
b10 %
1"
#1020
0"
#1025
b100 #
b11 %
1"
#1030
0"
#1035
b101 #
b100 %
1"
#1040
0"
#1045
b110 #
b101 %
1"
#1050
0"
#1055
b111 #
b110 %
1"
#1060
0"
#1065
b1000 #
b111 %
1"
#1070
0"
#1075
b1001 #
b1000 %
1"
#1080
0"
#1085
b1010 #
b1001 %
1"
#1090
0"
#1095
b1011 #
b1010 %
1"
#1100
0"
#1105
b1100 #
b1011 %
1"
#1110
0"
#1115
b1101 #
b1100 %
1"
#1120
0"
#1125
b1110 #
b1101 %
1"
#1130
0"
#1135
b1111 #
b1110 %
1"
#1140
0"
#1145
b10000 #
b1111 %
1"
#1150
0"
#1155
b10001 #
b10000 %
1"
#1160
0"
#1165
b10010 #
b10001 %
1"
#1170
0"
#1175
b10011 #
b10010 %
1"
#1180
0"
#1185
b10100 #
b10011 %
1"
#1190
0"
#1195
b10101 #
b10100 %
1"
#1200
0"
#1205
b10110 #
b10101 %
1"
#1210
0"
#1215
b10111 #
b10110 %
1"
#1220
0"
#1225
b11000 #
b10111 %
1"
#1230
0"
#1235
b11001 #
b11000 %
1"
#1240
0"
#1245
b11010 #
b11001 %
1"
#1250
0"
#1255
b11011 #
b11010 %
1"
#1260
0"
#1265
b11100 #
b11011 %
1"
#1270
0"
#1275
b11101 #
b11100 %
1"
#1280
0"
#1285
b11110 #
b11101 %
1"
#1290
0"
#1295
b11111 #
b11110 %
1"
#1300
0"
#1305
b100000 #
b11111 %
1"
#1310
0"
#1315
b100001 #
b100000 %
1"
#1320
0"
#1325
b100010 #
b100001 %
1"
#1330
0"
#1335
b100011 #
b100010 %
1"
#1340
0"
#1345
b100100 #
b100011 %
1"
#1350
0"
#1355
b100101 #
b100100 %
1"
#1360
0"
#1365
b100110 #
b100101 %
1"
#1370
0"
#1375
b100111 #
b100110 %
1"
#1380
0"
#1385
b101000 #
b100111 %
1"
#1390
0"
#1395
b101001 #
b101000 %
1"
#1400
0"
#1405
b101010 #
b101001 %
1"
#1410
0"
#1415
b101011 #
b101010 %
1"
#1420
0"
#1425
b101100 #
b101011 %
1"
#1430
0"
#1435
b101101 #
b101100 %
1"
#1440
0"
#1445
b101110 #
b101101 %
1"
#1450
0"
#1455
b101111 #
b101110 %
1"
#1460
0"
#1465
b110000 #
b101111 %
1"
#1470
0"
#1475
b110001 #
b110000 %
1"
#1480
0"
#1485
b110010 #
b110001 %
1"
#1490
0"
#1495
1!
1$
b1 #
b0 %
1"
#1500
0"
#1505
b10 #
b1 %
1"
#1510
0"
#1515
b11 #
b10 %
1"
#1520
0"
#1525
b100 #
b11 %
1"
#1530
0"
#1535
b101 #
b100 %
1"
#1540
0"
#1545
b110 #
b101 %
1"
#1550
0"
#1555
b111 #
b110 %
1"
#1560
0"
#1565
b1000 #
b111 %
1"
#1570
0"
#1575
b1001 #
b1000 %
1"
#1580
0"
#1585
b1010 #
b1001 %
1"
#1590
0"
#1595
b1011 #
b1010 %
1"
#1600
0"
#1605
b1100 #
b1011 %
1"
#1610
0"
#1615
b1101 #
b1100 %
1"
#1620
0"
#1625
b1110 #
b1101 %
1"
#1630
0"
#1635
b1111 #
b1110 %
1"
#1640
0"
#1645
b10000 #
b1111 %
1"
#1650
0"
#1655
b10001 #
b10000 %
1"
#1660
0"
#1665
b10010 #
b10001 %
1"
#1670
0"
#1675
b10011 #
b10010 %
1"
#1680
0"
#1685
b10100 #
b10011 %
1"
#1690
0"
#1695
b10101 #
b10100 %
1"
#1700
0"
#1705
b10110 #
b10101 %
1"
#1710
0"
#1715
b10111 #
b10110 %
1"
#1720
0"
#1725
b11000 #
b10111 %
1"
#1730
0"
#1735
b11001 #
b11000 %
1"
#1740
0"
#1745
b11010 #
b11001 %
1"
#1750
0"
#1755
b11011 #
b11010 %
1"
#1760
0"
#1765
b11100 #
b11011 %
1"
#1770
0"
#1775
b11101 #
b11100 %
1"
#1780
0"
#1785
b11110 #
b11101 %
1"
#1790
0"
#1795
b11111 #
b11110 %
1"
#1800
0"
#1805
b100000 #
b11111 %
1"
#1810
0"
#1815
b100001 #
b100000 %
1"
#1820
0"
#1825
b100010 #
b100001 %
1"
#1830
0"
#1835
b100011 #
b100010 %
1"
#1840
0"
#1845
b100100 #
b100011 %
1"
#1850
0"
#1855
b100101 #
b100100 %
1"
#1860
0"
#1865
b100110 #
b100101 %
1"
#1870
0"
#1875
b100111 #
b100110 %
1"
#1880
0"
#1885
b101000 #
b100111 %
1"
#1890
0"
#1895
b101001 #
b101000 %
1"
#1900
0"
#1905
b101010 #
b101001 %
1"
#1910
0"
#1915
b101011 #
b101010 %
1"
#1920
0"
#1925
b101100 #
b101011 %
1"
#1930
0"
#1935
b101101 #
b101100 %
1"
#1940
0"
#1945
b101110 #
b101101 %
1"
#1950
0"
#1955
b101111 #
b101110 %
1"
#1960
0"
#1965
b110000 #
b101111 %
1"
#1970
0"
#1975
b110001 #
b110000 %
1"
#1980
0"
#1985
b110010 #
b110001 %
1"
#1990
0"
#1995
0!
0$
b1 #
b0 %
1"
#2000
0"
#2005
b10 #
b1 %
1"
#2010
0"
#2015
b11 #
b10 %
1"
#2020
0"
#2025
b100 #
b11 %
1"
#2030
0"
#2035
b101 #
b100 %
1"
#2040
0"
#2045
b110 #
b101 %
1"
#2050
0"
#2055
b111 #
b110 %
1"
#2060
0"
#2065
b1000 #
b111 %
1"
#2070
0"
#2075
b1001 #
b1000 %
1"
#2080
0"
#2085
b1010 #
b1001 %
1"
#2090
0"
#2095
b1011 #
b1010 %
1"
#2100
0"
#2105
b1100 #
b1011 %
1"
#2110
0"
#2115
b1101 #
b1100 %
1"
#2120
0"
#2125
b1110 #
b1101 %
1"
#2130
0"
#2135
b1111 #
b1110 %
1"
#2140
0"
#2145
b10000 #
b1111 %
1"
#2150
0"
#2155
b10001 #
b10000 %
1"
#2160
0"
#2165
b10010 #
b10001 %
1"
#2170
0"
#2175
b10011 #
b10010 %
1"
#2180
0"
#2185
b10100 #
b10011 %
1"
#2190
0"
#2195
b10101 #
b10100 %
1"
#2200
0"
#2205
b10110 #
b10101 %
1"
#2210
0"
#2215
b10111 #
b10110 %
1"
#2220
0"
#2225
b11000 #
b10111 %
1"
#2230
0"
#2235
b11001 #
b11000 %
1"
#2240
0"
#2245
b11010 #
b11001 %
1"
#2250
0"
#2255
b11011 #
b11010 %
1"
#2260
0"
#2265
b11100 #
b11011 %
1"
#2270
0"
#2275
b11101 #
b11100 %
1"
#2280
0"
#2285
b11110 #
b11101 %
1"
#2290
0"
#2295
b11111 #
b11110 %
1"
#2300
0"
#2305
b100000 #
b11111 %
1"
#2310
0"
#2315
b100001 #
b100000 %
1"
#2320
0"
#2325
b100010 #
b100001 %
1"
#2330
0"
#2335
b100011 #
b100010 %
1"
#2340
0"
#2345
b100100 #
b100011 %
1"
#2350
0"
#2355
b100101 #
b100100 %
1"
#2360
0"
#2365
b100110 #
b100101 %
1"
#2370
0"
#2375
b100111 #
b100110 %
1"
#2380
0"
#2385
b101000 #
b100111 %
1"
#2390
0"
#2395
b101001 #
b101000 %
1"
#2400
0"
#2405
b101010 #
b101001 %
1"
#2410
0"
#2415
b101011 #
b101010 %
1"
#2420
0"
#2425
b101100 #
b101011 %
1"
#2430
0"
#2435
b101101 #
b101100 %
1"
#2440
0"
#2445
b101110 #
b101101 %
1"
#2450
0"
#2455
b101111 #
b101110 %
1"
#2460
0"
#2465
b110000 #
b101111 %
1"
#2470
0"
#2475
b110001 #
b110000 %
1"
#2480
0"
#2485
b110010 #
b110001 %
1"
#2490
0"
#2495
1!
1$
b1 #
b0 %
1"
#2500
0"
#2505
b10 #
b1 %
1"
#2510
0"
#2515
b11 #
b10 %
1"
#2520
0"
#2525
b100 #
b11 %
1"
#2530
0"
#2535
b101 #
b100 %
1"
#2540
0"
#2545
b110 #
b101 %
1"
#2550
0"
#2555
b111 #
b110 %
1"
#2560
0"
#2565
b1000 #
b111 %
1"
#2570
0"
#2575
b1001 #
b1000 %
1"
#2580
0"
#2585
b1010 #
b1001 %
1"
#2590
0"
#2595
b1011 #
b1010 %
1"
#2600
0"
#2605
b1100 #
b1011 %
1"
#2610
0"
#2615
b1101 #
b1100 %
1"
#2620
0"
#2625
b1110 #
b1101 %
1"
#2630
0"
#2635
b1111 #
b1110 %
1"
#2640
0"
#2645
b10000 #
b1111 %
1"
#2650
0"
#2655
b10001 #
b10000 %
1"
#2660
0"
#2665
b10010 #
b10001 %
1"
#2670
0"
#2675
b10011 #
b10010 %
1"
#2680
0"
#2685
b10100 #
b10011 %
1"
#2690
0"
#2695
b10101 #
b10100 %
1"
#2700
0"
#2705
b10110 #
b10101 %
1"
#2710
0"
#2715
b10111 #
b10110 %
1"
#2720
0"
#2725
b11000 #
b10111 %
1"
#2730
0"
#2735
b11001 #
b11000 %
1"
#2740
0"
#2745
b11010 #
b11001 %
1"
#2750
0"
#2755
b11011 #
b11010 %
1"
#2760
0"
#2765
b11100 #
b11011 %
1"
#2770
0"
#2775
b11101 #
b11100 %
1"
#2780
0"
#2785
b11110 #
b11101 %
1"
#2790
0"
#2795
b11111 #
b11110 %
1"
#2800
0"
#2805
b100000 #
b11111 %
1"
#2810
0"
#2815
b100001 #
b100000 %
1"
#2820
0"
#2825
b100010 #
b100001 %
1"
#2830
0"
#2835
b100011 #
b100010 %
1"
#2840
0"
#2845
b100100 #
b100011 %
1"
#2850
0"
#2855
b100101 #
b100100 %
1"
#2860
0"
#2865
b100110 #
b100101 %
1"
#2870
0"
#2875
b100111 #
b100110 %
1"
#2880
0"
#2885
b101000 #
b100111 %
1"
#2890
0"
#2895
b101001 #
b101000 %
1"
#2900
0"
#2905
b101010 #
b101001 %
1"
#2910
0"
#2915
b101011 #
b101010 %
1"
#2920
0"
#2925
b101100 #
b101011 %
1"
#2930
0"
#2935
b101101 #
b101100 %
1"
#2940
0"
#2945
b101110 #
b101101 %
1"
#2950
0"
#2955
b101111 #
b101110 %
1"
#2960
0"
#2965
b110000 #
b101111 %
1"
#2970
0"
#2975
b110001 #
b110000 %
1"
#2980
0"
#2985
b110010 #
b110001 %
1"
#2990
0"
#2995
0!
0$
b1 #
b0 %
1"
#3000
0"
#3005
b10 #
b1 %
1"
#3010
0"
#3015
b11 #
b10 %
1"
#3020
0"
#3025
b100 #
b11 %
1"
#3030
0"
#3035
b101 #
b100 %
1"
#3040
0"
#3045
b110 #
b101 %
1"
#3050
0"
#3055
b111 #
b110 %
1"
#3060
0"
#3065
b1000 #
b111 %
1"
#3070
0"
#3075
b1001 #
b1000 %
1"
#3080
0"
#3085
b1010 #
b1001 %
1"
#3090
0"
#3095
b1011 #
b1010 %
1"
#3100
0"
#3105
b1100 #
b1011 %
1"
#3110
0"
#3115
b1101 #
b1100 %
1"
#3120
0"
#3125
b1110 #
b1101 %
1"
#3130
0"
#3135
b1111 #
b1110 %
1"
#3140
0"
#3145
b10000 #
b1111 %
1"
#3150
0"
#3155
b10001 #
b10000 %
1"
#3160
0"
#3165
b10010 #
b10001 %
1"
#3170
0"
#3175
b10011 #
b10010 %
1"
#3180
0"
#3185
b10100 #
b10011 %
1"
#3190
0"
#3195
b10101 #
b10100 %
1"
#3200
0"
#3205
b10110 #
b10101 %
1"
#3210
0"
#3215
b10111 #
b10110 %
1"
#3220
0"
#3225
b11000 #
b10111 %
1"
#3230
0"
#3235
b11001 #
b11000 %
1"
#3240
0"
#3245
b11010 #
b11001 %
1"
#3250
0"
#3255
b11011 #
b11010 %
1"
#3260
0"
#3265
b11100 #
b11011 %
1"
#3270
0"
#3275
b11101 #
b11100 %
1"
#3280
0"
#3285
b11110 #
b11101 %
1"
#3290
0"
#3295
b11111 #
b11110 %
1"
#3300
0"
#3305
b100000 #
b11111 %
1"
#3310
0"
#3315
b100001 #
b100000 %
1"
#3320
0"
#3325
b100010 #
b100001 %
1"
#3330
0"
#3335
b100011 #
b100010 %
1"
#3340
0"
#3345
b100100 #
b100011 %
1"
#3350
0"
#3355
b100101 #
b100100 %
1"
#3360
0"
#3365
b100110 #
b100101 %
1"
#3370
0"
#3375
b100111 #
b100110 %
1"
#3380
0"
#3385
b101000 #
b100111 %
1"
#3390
0"
#3395
b101001 #
b101000 %
1"
#3400
0"
#3405
b101010 #
b101001 %
1"
#3410
0"
#3415
b101011 #
b101010 %
1"
#3420
0"
#3425
b101100 #
b101011 %
1"
#3430
0"
#3435
b101101 #
b101100 %
1"
#3440
0"
#3445
b101110 #
b101101 %
1"
#3450
0"
#3455
b101111 #
b101110 %
1"
#3460
0"
#3465
b110000 #
b101111 %
1"
#3470
0"
#3475
b110001 #
b110000 %
1"
#3480
0"
#3485
b110010 #
b110001 %
1"
#3490
0"
#3495
1!
1$
b1 #
b0 %
1"
#3500
0"
#3505
b10 #
b1 %
1"
#3510
0"
#3515
b11 #
b10 %
1"
#3520
0"
#3525
b100 #
b11 %
1"
#3530
0"
#3535
b101 #
b100 %
1"
#3540
0"
#3545
b110 #
b101 %
1"
#3550
0"
#3555
b111 #
b110 %
1"
#3560
0"
#3565
b1000 #
b111 %
1"
#3570
0"
#3575
b1001 #
b1000 %
1"
#3580
0"
#3585
b1010 #
b1001 %
1"
#3590
0"
#3595
b1011 #
b1010 %
1"
#3600
0"
#3605
b1100 #
b1011 %
1"
#3610
0"
#3615
b1101 #
b1100 %
1"
#3620
0"
#3625
b1110 #
b1101 %
1"
#3630
0"
#3635
b1111 #
b1110 %
1"
#3640
0"
#3645
b10000 #
b1111 %
1"
#3650
0"
#3655
b10001 #
b10000 %
1"
#3660
0"
#3665
b10010 #
b10001 %
1"
#3670
0"
#3675
b10011 #
b10010 %
1"
#3680
0"
#3685
b10100 #
b10011 %
1"
#3690
0"
#3695
b10101 #
b10100 %
1"
#3700
0"
#3705
b10110 #
b10101 %
1"
#3710
0"
#3715
b10111 #
b10110 %
1"
#3720
0"
#3725
b11000 #
b10111 %
1"
#3730
0"
#3735
b11001 #
b11000 %
1"
#3740
0"
#3745
b11010 #
b11001 %
1"
#3750
0"
#3755
b11011 #
b11010 %
1"
#3760
0"
#3765
b11100 #
b11011 %
1"
#3770
0"
#3775
b11101 #
b11100 %
1"
#3780
0"
#3785
b11110 #
b11101 %
1"
#3790
0"
#3795
b11111 #
b11110 %
1"
#3800
0"
#3805
b100000 #
b11111 %
1"
#3810
0"
#3815
b100001 #
b100000 %
1"
#3820
0"
#3825
b100010 #
b100001 %
1"
#3830
0"
#3835
b100011 #
b100010 %
1"
#3840
0"
#3845
b100100 #
b100011 %
1"
#3850
0"
#3855
b100101 #
b100100 %
1"
#3860
0"
#3865
b100110 #
b100101 %
1"
#3870
0"
#3875
b100111 #
b100110 %
1"
#3880
0"
#3885
b101000 #
b100111 %
1"
#3890
0"
#3895
b101001 #
b101000 %
1"
#3900
0"
#3905
b101010 #
b101001 %
1"
#3910
0"
#3915
b101011 #
b101010 %
1"
#3920
0"
#3925
b101100 #
b101011 %
1"
#3930
0"
#3935
b101101 #
b101100 %
1"
#3940
0"
#3945
b101110 #
b101101 %
1"
#3950
0"
#3955
b101111 #
b101110 %
1"
#3960
0"
#3965
b110000 #
b101111 %
1"
#3970
0"
#3975
b110001 #
b110000 %
1"
#3980
0"
#3985
b110010 #
b110001 %
1"
#3990
0"
#3995
0!
0$
b1 #
b0 %
1"
#4000
0"
#4005
b10 #
b1 %
1"
#4010
0"
#4015
b11 #
b10 %
1"
#4020
0"
#4025
b100 #
b11 %
1"
#4030
0"
#4035
b101 #
b100 %
1"
#4040
0"
#4045
b110 #
b101 %
1"
#4050
0"
#4055
b111 #
b110 %
1"
#4060
0"
#4065
b1000 #
b111 %
1"
#4070
0"
#4075
b1001 #
b1000 %
1"
#4080
0"
#4085
b1010 #
b1001 %
1"
#4090
0"
#4095
b1011 #
b1010 %
1"
#4100
0"
#4105
b1100 #
b1011 %
1"
#4110
0"
#4115
b1101 #
b1100 %
1"
#4120
0"
#4125
b1110 #
b1101 %
1"
#4130
0"
#4135
b1111 #
b1110 %
1"
#4140
0"
#4145
b10000 #
b1111 %
1"
#4150
0"
#4155
b10001 #
b10000 %
1"
#4160
0"
#4165
b10010 #
b10001 %
1"
#4170
0"
#4175
b10011 #
b10010 %
1"
#4180
0"
#4185
b10100 #
b10011 %
1"
#4190
0"
#4195
b10101 #
b10100 %
1"
#4200
0"
#4205
b10110 #
b10101 %
1"
#4210
0"
#4215
b10111 #
b10110 %
1"
#4220
0"
#4225
b11000 #
b10111 %
1"
#4230
0"
#4235
b11001 #
b11000 %
1"
#4240
0"
#4245
b11010 #
b11001 %
1"
#4250
0"
#4255
b11011 #
b11010 %
1"
#4260
0"
#4265
b11100 #
b11011 %
1"
#4270
0"
#4275
b11101 #
b11100 %
1"
#4280
0"
#4285
b11110 #
b11101 %
1"
#4290
0"
#4295
b11111 #
b11110 %
1"
#4300
0"
#4305
b100000 #
b11111 %
1"
#4310
0"
#4315
b100001 #
b100000 %
1"
#4320
0"
#4325
b100010 #
b100001 %
1"
#4330
0"
#4335
b100011 #
b100010 %
1"
#4340
0"
#4345
b100100 #
b100011 %
1"
#4350
0"
#4355
b100101 #
b100100 %
1"
#4360
0"
#4365
b100110 #
b100101 %
1"
#4370
0"
#4375
b100111 #
b100110 %
1"
#4380
0"
#4385
b101000 #
b100111 %
1"
#4390
0"
#4395
b101001 #
b101000 %
1"
#4400
0"
#4405
b101010 #
b101001 %
1"
#4410
0"
#4415
b101011 #
b101010 %
1"
#4420
0"
#4425
b101100 #
b101011 %
1"
#4430
0"
#4435
b101101 #
b101100 %
1"
#4440
0"
#4445
b101110 #
b101101 %
1"
#4450
0"
#4455
b101111 #
b101110 %
1"
#4460
0"
#4465
b110000 #
b101111 %
1"
#4470
0"
#4475
b110001 #
b110000 %
1"
#4480
0"
#4485
b110010 #
b110001 %
1"
#4490
0"
#4495
1!
1$
b1 #
b0 %
1"
#4500
0"
#4505
b10 #
b1 %
1"
#4510
0"
#4515
b11 #
b10 %
1"
#4520
0"
#4525
b100 #
b11 %
1"
#4530
0"
#4535
b101 #
b100 %
1"
#4540
0"
#4545
b110 #
b101 %
1"
#4550
0"
#4555
b111 #
b110 %
1"
#4560
0"
#4565
b1000 #
b111 %
1"
#4570
0"
#4575
b1001 #
b1000 %
1"
#4580
0"
#4585
b1010 #
b1001 %
1"
#4590
0"
#4595
b1011 #
b1010 %
1"
#4600
0"
#4605
b1100 #
b1011 %
1"
#4610
0"
#4615
b1101 #
b1100 %
1"
#4620
0"
#4625
b1110 #
b1101 %
1"
#4630
0"
#4635
b1111 #
b1110 %
1"
#4640
0"
#4645
b10000 #
b1111 %
1"
#4650
0"
#4655
b10001 #
b10000 %
1"
#4660
0"
#4665
b10010 #
b10001 %
1"
#4670
0"
#4675
b10011 #
b10010 %
1"
#4680
0"
#4685
b10100 #
b10011 %
1"
#4690
0"
#4695
b10101 #
b10100 %
1"
#4700
0"
#4705
b10110 #
b10101 %
1"
#4710
0"
#4715
b10111 #
b10110 %
1"
#4720
0"
#4725
b11000 #
b10111 %
1"
#4730
0"
#4735
b11001 #
b11000 %
1"
#4740
0"
#4745
b11010 #
b11001 %
1"
#4750
0"
#4755
b11011 #
b11010 %
1"
#4760
0"
#4765
b11100 #
b11011 %
1"
#4770
0"
#4775
b11101 #
b11100 %
1"
#4780
0"
#4785
b11110 #
b11101 %
1"
#4790
0"
#4795
b11111 #
b11110 %
1"
#4800
0"
#4805
b100000 #
b11111 %
1"
#4810
0"
#4815
b100001 #
b100000 %
1"
#4820
0"
#4825
b100010 #
b100001 %
1"
#4830
0"
#4835
b100011 #
b100010 %
1"
#4840
0"
#4845
b100100 #
b100011 %
1"
#4850
0"
#4855
b100101 #
b100100 %
1"
#4860
0"
#4865
b100110 #
b100101 %
1"
#4870
0"
#4875
b100111 #
b100110 %
1"
#4880
0"
#4885
b101000 #
b100111 %
1"
#4890
0"
#4895
b101001 #
b101000 %
1"
#4900
0"
#4905
b101010 #
b101001 %
1"
#4910
0"
#4915
b101011 #
b101010 %
1"
#4920
0"
#4925
b101100 #
b101011 %
1"
#4930
0"
#4935
b101101 #
b101100 %
1"
#4940
0"
#4945
b101110 #
b101101 %
1"
#4950
0"
#4955
b101111 #
b101110 %
1"
#4960
0"
#4965
b110000 #
b101111 %
1"
#4970
0"
#4975
b110001 #
b110000 %
1"
#4980
0"
#4985
b110010 #
b110001 %
1"
#4990
0"
#4995
0!
0$
b1 #
b0 %
1"
#5000
0"
#5005
b10 #
b1 %
1"
#5010
0"
#5015
b11 #
b10 %
1"
#5020
0"
#5025
b100 #
b11 %
1"
#5030
0"
#5035
b101 #
b100 %
1"
#5040
0"
#5045
b110 #
b101 %
1"
#5050
0"
#5055
b111 #
b110 %
1"
#5060
0"
#5065
b1000 #
b111 %
1"
#5070
0"
#5075
b1001 #
b1000 %
1"
#5080
0"
#5085
b1010 #
b1001 %
1"
#5090
0"
#5095
b1011 #
b1010 %
1"
#5100
0"
#5105
b1100 #
b1011 %
1"
#5110
0"
#5115
b1101 #
b1100 %
1"
#5120
0"
#5125
b1110 #
b1101 %
1"
#5130
0"
#5135
b1111 #
b1110 %
1"
#5140
0"
#5145
b10000 #
b1111 %
1"
#5150
0"
#5155
b10001 #
b10000 %
1"
#5160
0"
#5165
b10010 #
b10001 %
1"
#5170
0"
#5175
b10011 #
b10010 %
1"
#5180
0"
#5185
b10100 #
b10011 %
1"
#5190
0"
#5195
b10101 #
b10100 %
1"
#5200
0"
#5205
b10110 #
b10101 %
1"
#5210
0"
#5215
b10111 #
b10110 %
1"
#5220
0"
#5225
b11000 #
b10111 %
1"
#5230
0"
#5235
b11001 #
b11000 %
1"
#5240
0"
#5245
b11010 #
b11001 %
1"
#5250
0"
#5255
b11011 #
b11010 %
1"
#5260
0"
#5265
b11100 #
b11011 %
1"
#5270
0"
#5275
b11101 #
b11100 %
1"
#5280
0"
#5285
b11110 #
b11101 %
1"
#5290
0"
#5295
b11111 #
b11110 %
1"
#5300
0"
#5305
b100000 #
b11111 %
1"
#5310
0"
#5315
b100001 #
b100000 %
1"
#5320
0"
#5325
b100010 #
b100001 %
1"
#5330
0"
#5335
b100011 #
b100010 %
1"
#5340
0"
#5345
b100100 #
b100011 %
1"
#5350
0"
#5355
b100101 #
b100100 %
1"
#5360
0"
#5365
b100110 #
b100101 %
1"
#5370
0"
#5375
b100111 #
b100110 %
1"
#5380
0"
#5385
b101000 #
b100111 %
1"
#5390
0"
#5395
b101001 #
b101000 %
1"
#5400
0"
#5405
b101010 #
b101001 %
1"
#5410
0"
#5415
b101011 #
b101010 %
1"
#5420
0"
#5425
b101100 #
b101011 %
1"
#5430
0"
#5435
b101101 #
b101100 %
1"
#5440
0"
#5445
b101110 #
b101101 %
1"
#5450
0"
#5455
b101111 #
b101110 %
1"
#5460
0"
#5465
b110000 #
b101111 %
1"
#5470
0"
#5475
b110001 #
b110000 %
1"
#5480
0"
#5485
b110010 #
b110001 %
1"
#5490
0"
#5495
1!
1$
b1 #
b0 %
1"
#5500
0"
#5505
b10 #
b1 %
1"
#5510
0"
#5515
b11 #
b10 %
1"
#5520
0"
#5525
b100 #
b11 %
1"
#5530
0"
#5535
b101 #
b100 %
1"
#5540
0"
#5545
b110 #
b101 %
1"
#5550
0"
#5555
b111 #
b110 %
1"
#5560
0"
#5565
b1000 #
b111 %
1"
#5570
0"
#5575
b1001 #
b1000 %
1"
#5580
0"
#5585
b1010 #
b1001 %
1"
