projeto/nivel1/nivel2/nivel3/counter0_7.v
module counter7 (input clk,      
                  input clear,              
                  output reg clk_out);    
 
  reg [3:0]out;  //criando uma variavel auxiliar para servir como contador
  initial begin
      clk_out <= 0;
      out <= 0;
  end

    always @ (posedge clk) begin //sempre na borda de subida entramos no always
        if(clear)begin  
            if (out == 3) begin// qaundo chegar em 4 a saida fica '1'
                clk_out <= 1;
                out <= out + 1; 
            end
        

            else if (out == 7) // se o contador chegar em 7 e o comando clear n for '0' ele continua no 7.
                out <=7;
            else    
                out <= out + 1;
        end
        else  begin
            if(out==7)begin // clear ativo em nivel BAIXO envia o 1 e atualiza pra zero o contador.   
                out <= out + 1;
                clk_out <=0;
            end
        end
    
  end
endmodule

projeto/nivel1/nivel2/nivel3/counter0_7_tb.v
module counter7_tb;  
  reg clk;                     // Declare an internal TB variable called clk to drive clock to the design  
  reg clear;                    // Declare an internal TB variable called clear to drive active low reset to design  
  wire clk_out;              // Declare a wire to connect to design output  
  
  // Instantiate counter design and connect with Testbench variables  
  counter7   c0 (clk,clear,clk_out);  
  
  // Generate a clock that should be driven to design  
  // This clock will flip its value every 5ns -> time period = 10ns -> freq = 100 MHz  
   
 always 
    #5 clk = ~clk;  
  
  // This initial block forms the stimulus of the testbench  
    initial begin  
    // Initialize testbench variables to 0 at start of simulation  
        clk <= 0;  
        clear <= 1;  
  
    // Drive rest of the stimulus, reset is asserted in between  
        #10   clear <= 1;  
        #80   clear <= 1;  
        #50   clear <= 0;  
  
    // Finish the stimulus after 200ns  
        #20 $finish;  
    end
        initial
            $monitor("clk=%b,clear=%b,clk_out=%b",clk,clear,clk_out);
        initial begin
            $dumpfile("counter7_tb.vcd");
            $dumpvars(0,counter7_tb);
            end

endmodule

projeto/nivel1/nivel2/nivel3/counter7_tb.vcd
$date
	Fri Apr 30 00:39:49 2021
$end
$version
	Icarus Verilog
$end
$timescale
	1s
$end
$scope module counter7_tb $end
$var wire 1 ! clk_out $end
$var reg 1 " clear $end
$var reg 1 # clk $end
$scope module c0 $end
$var wire 1 " clear $end
$var wire 1 # clk $end
$var reg 1 ! clk_out $end
$var reg 4 $ out [3:0] $end
$upscope $end
$upscope $end
$enddefinitions $end
#0
$dumpvars
b0 $
0#
1"
0!
$end
#5
b1 $
1#
#10
0#
#15
b10 $
1#
#20
0#
#25
b11 $
1#
#30
0#
#35
b100 $
1!
1#
#40
0#
#45
b101 $
1#
#50
0#
#55
b110 $
1#
#60
0#
#65
b111 $
1#
#70
0#
#75
1#
#80
0#
#85
1#
#90
0#
#95
1#
#100
0#
#105
1#
#110
0#
#115
1#
#120
0#
#125
1#
#130
0#
#135
1#
#140
0"
0#
#145
0!
b1000 $
1#
