projeto/nivel1/nivel2/nivel3/mux2to1.v
module mux2to1 (
    input wire selection,
    input wire d0,
    input wire d1,
    output reg out
);

    always @(selection or d0 or d1)
        begin
            if(selection)
                out = d1;
            else
                out = d0;
        end
    
endmodule

projeto/nivel1/nivel2/nivel3/mux2to1_tb.v
module mux2to1_tb();

reg selection;
reg d0;
reg d1;
wire out;

mux2to1 mux(selection,d0,d1,out);

always #10 selection=~selection;

initial
    begin
        selection <= 0;
        d0<=1'b0;
        d1<=1'b0;
        #5d0=1'b0;
        #5d1=1'b0;
        #5d0=1'b1;
        #5d1=1'b0;
        #5d0=1'b1;
        #5d1=1'b1;
        #5d0=1'b0;
        #5d1=1'b1;
        #5d0=1'b0;
        #5d1=1'b0;
        #100 $finish;
    end
        
       
        

initial
    begin
        $dumpfile("mux2to1_tb.vcd");
        $dumpvars(0,mux2to1_tb);
    end
endmodule

projeto/nivel1/nivel2/nivel3/mux2to1_tb.vcd
$date
	Fri Apr 30 00:54:16 2021
$end
$version
	Icarus Verilog
$end
$timescale
	1s
$end
$scope module mux2to1_tb $end
$var wire 1 ! out $end
$var reg 1 " d0 $end
$var reg 1 # d1 $end
$var reg 1 $ selection $end
$scope module mux $end
$var wire 1 " d0 $end
$var wire 1 # d1 $end
$var wire 1 $ selection $end
$var reg 1 ! out $end
$upscope $end
$upscope $end
$enddefinitions $end
#0
$dumpvars
0$
0#
0"
0!
$end
#10
1$
#15
1"
#20
1!
0$
#30
1#
1$
#35
0"
#40
0!
0$
#50
0#
1$
#60
0$
#70
1$
#80
0$
#90
1$
#100
0$
#110
1$
#120
0$
#130
1$
#140
0$
#150
1$
